bos_incidents/__init__.py
bos_incidents/cli.py
bos_incidents/cli_incidents.py
bos_incidents/config-defaults.yaml
bos_incidents/datestring.py
bos_incidents/event-schema.json
bos_incidents/exceptions.py
bos_incidents/factory.py
bos_incidents/format.py
bos_incidents/incident-schema-draft6.json
bos_incidents/incident-schema.json
bos_incidents/mongodb_storage.py
bos_incidents/ui.py
bos_incidents/validator.py
bos_incidents-0.4.1.dist-info/LICENSE.txt
bos_incidents-0.4.1.dist-info/METADATA
bos_incidents-0.4.1.dist-info/WHEEL
bos_incidents-0.4.1.dist-info/entry_points.txt
bos_incidents-0.4.1.dist-info/top_level.txt
bos_incidents-0.4.1.dist-info/RECORD
