Metadata-Version: 2.1
Name: bos-incidents
Version: 0.4.1
Summary: Private module for BOS incident storage
Home-page: http://pbsa.info
Author: Peerplays Community
Maintainer: Peerplays Community
License: UNKNOWN
Download-URL: https://github.com/pbsa/bos-incidents/tarball/0.4.1
Keywords: peerplays,bos
Platform: UNKNOWN
Classifier: License :: OSI Approved :: GNU General Public License v3 (GPLv3)
Classifier: Operating System :: OS Independent
Classifier: Programming Language :: Python :: 3
Classifier: Development Status :: 3 - Alpha
Classifier: Intended Audience :: Developers
Requires-Dist: pymongo
Requires-Dist: pyyaml
Requires-Dist: jsonschema
Requires-Dist: strict-rfc3339
Requires-Dist: pytz
Requires-Dist: click
Requires-Dist: click-datetime
Requires-Dist: tqdm
Requires-Dist: bookiesports
